{
  "customers": [
    {
      "id": 1,
      "name": "Nicolas, Hartmann and McKenzie",
      "catchPhrase": "Networked human-resource open architecture"
    },
    {
      "id": 2,
      "name": "Kunze - Brakus",
      "catchPhrase": "Exclusive actuating task-force"
    },
    {
      "id": 3,
      "name": "Rutherford LLC",
      "catchPhrase": "Reduced client-server open system"
    },
    {
      "id": 4,
      "name": "Greenholt - Kuhlman",
      "catchPhrase": "Polarised asynchronous standardization"
    },
    {
      "id": 5,
      "name": "Welch - Anderson",
      "catchPhrase": "Cross-platform upward-trending knowledge user"
    },
    {
      "id": 6,
      "name": "Ferry - Keeling",
      "catchPhrase": "Phased demand-driven protocol"
    },
    {
      "id": 7,
      "name": "Dare - Krajcik",
      "catchPhrase": "Function-based empowering Graphical User Interface"
    },
    {
      "id": 8,
      "name": "Cummings and Sons",
      "catchPhrase": "Automated responsive knowledge base"
    },
    {
      "id": 9,
      "name": "Olson, Ebert and Koepp",
      "catchPhrase": "Enhanced bandwidth-monitored extranet"
    },
    {
      "id": 10,
      "name": "Bruen Inc",
      "catchPhrase": "Grass-roots executive hierarchy"
    },
    {
      "id": 11,
      "name": "Kertzmann - Yundt",
      "catchPhrase": "Synchronised systematic open architecture"
    },
    {
      "id": 12,
      "name": "Fadel - Schulist",
      "catchPhrase": "Digitized neutral software"
    },
    {
      "id": 13,
      "name": "Beahan, O'Reilly and Pfannerstill",
      "catchPhrase": "Universal mission-critical alliance"
    },
    {
      "id": 14,
      "name": "Jacobson Inc",
      "catchPhrase": "Progressive foreground product"
    },
    {
      "id": 15,
      "name": "Toy, Sporer and Jacobs",
      "catchPhrase": "Persevering bottom-line circuit"
    },
    {
      "id": 16,
      "name": "Hoeger and Sons",
      "catchPhrase": "Front-line fresh-thinking definition"
    },
    {
      "id": 17,
      "name": "Torphy - Moen",
      "catchPhrase": "Multi-channelled intermediate focus group"
    },
    {
      "id": 18,
      "name": "Greenholt, Beer and Volkman",
      "catchPhrase": "Face to face interactive task-force"
    },
    {
      "id": 19,
      "name": "Ward - Hayes",
      "catchPhrase": "Profit-focused object-oriented strategy"
    },
    {
      "id": 20,
      "name": "Fadel - Rogahn",
      "catchPhrase": "Reduced maximized success"
    },
    {
      "id": 21,
      "name": "Hayes, Nolan and Gleichner",
      "catchPhrase": "Ergonomic asymmetric circuit"
    },
    {
      "id": 22,
      "name": "Barton and Sons",
      "catchPhrase": "User-centric bi-directional capability"
    },
    {
      "id": 23,
      "name": "Lockman Inc",
      "catchPhrase": "Up-sized fault-tolerant array"
    },
    {
      "id": 24,
      "name": "Howe - Schimmel",
      "catchPhrase": "Inverse scalable contingency"
    },
    {
      "id": 25,
      "name": "Swaniawski - Pagac",
      "catchPhrase": "Triple-buffered executive hierarchy"
    },
    {
      "id": 26,
      "name": "Auer, McKenzie and Gusikowski",
      "catchPhrase": "Visionary holistic archive"
    },
    {
      "id": 27,
      "name": "Cummings, Heathcote and Williamson",
      "catchPhrase": "Multi-lateral user-facing toolset"
    },
    {
      "id": 28,
      "name": "Padberg, Jenkins and Paucek",
      "catchPhrase": "Enhanced multimedia emulation"
    },
    {
      "id": 29,
      "name": "Miller Inc",
      "catchPhrase": "Business-focused homogeneous data-warehouse"
    },
    {
      "id": 30,
      "name": "Kirlin LLC",
      "catchPhrase": "Secured clear-thinking orchestration"
    },
    {
      "id": 31,
      "name": "Altenwerth and Sons",
      "catchPhrase": "Robust system-worthy groupware"
    },
    {
      "id": 32,
      "name": "Renner LLC",
      "catchPhrase": "Digitized systematic function"
    },
    {
      "id": 33,
      "name": "Blanda - Buckridge",
      "catchPhrase": "Inverse dynamic concept"
    },
    {
      "id": 34,
      "name": "Bechtelar and Sons",
      "catchPhrase": "Realigned impactful emulation"
    },
    {
      "id": 35,
      "name": "Turner Inc",
      "catchPhrase": "Quality-focused object-oriented matrix"
    },
    {
      "id": 36,
      "name": "Nienow - Ebert",
      "catchPhrase": "Reverse-engineered asymmetric instruction set"
    },
    {
      "id": 37,
      "name": "Dare and Sons",
      "catchPhrase": "Public-key asynchronous Graphic Interface"
    },
    {
      "id": 38,
      "name": "Pfeffer, Pacocha and Rolfson",
      "catchPhrase": "Reverse-engineered object-oriented productivity"
    },
    {
      "id": 39,
      "name": "O'Kon, Hegmann and Beatty",
      "catchPhrase": "Function-based motivating Graphic Interface"
    },
    {
      "id": 40,
      "name": "Muller, Russel and Durgan",
      "catchPhrase": "Configurable local standardization"
    },
    {
      "id": 41,
      "name": "Murazik, Wyman and Johns",
      "catchPhrase": "Pre-emptive systematic solution"
    },
    {
      "id": 42,
      "name": "Volkman and Sons",
      "catchPhrase": "Persistent reciprocal infrastructure"
    },
    {
      "id": 43,
      "name": "Mayer, Jones and Huel",
      "catchPhrase": "Reactive discrete matrix"
    },
    {
      "id": 44,
      "name": "Stamm Inc",
      "catchPhrase": "Assimilated bi-directional synergy"
    },
    {
      "id": 45,
      "name": "Bogan - Howell",
      "catchPhrase": "Networked web-enabled approach"
    },
    {
      "id": 46,
      "name": "Bailey Group",
      "catchPhrase": "Multi-lateral stable superstructure"
    },
    {
      "id": 47,
      "name": "Gutkowski Inc",
      "catchPhrase": "Streamlined high-level adapter"
    },
    {
      "id": 48,
      "name": "Goyette and Sons",
      "catchPhrase": "Organic 24 hour intranet"
    },
    {
      "id": 49,
      "name": "Funk LLC",
      "catchPhrase": "User-centric eco-centric moratorium"
    },
    {
      "id": 50,
      "name": "Hane Group",
      "catchPhrase": "De-engineered optimizing Graphic Interface"
    },
    {
      "id": 51,
      "name": "Okuneva, Strosin and Trantow",
      "catchPhrase": "Front-line leading edge help-desk"
    },
    {
      "id": 52,
      "name": "Schamberger - Beier",
      "catchPhrase": "Robust upward-trending internet solution"
    },
    {
      "id": 53,
      "name": "Daugherty, Fisher and Bayer",
      "catchPhrase": "Grass-roots actuating parallelism"
    },
    {
      "id": 54,
      "name": "Mitchell - Feest",
      "catchPhrase": "Re-contextualized encompassing approach"
    },
    {
      "id": 55,
      "name": "Beier Inc",
      "catchPhrase": "Inverse zero tolerance projection"
    },
    {
      "id": 56,
      "name": "O'Hara - O'Connell",
      "catchPhrase": "Down-sized context-sensitive artificial intelligence"
    },
    {
      "id": 57,
      "name": "Lowe Group",
      "catchPhrase": "Distributed upward-trending adapter"
    },
    {
      "id": 58,
      "name": "Beatty Group",
      "catchPhrase": "User-friendly systematic forecast"
    },
    {
      "id": 59,
      "name": "Mann - McKenzie",
      "catchPhrase": "Up-sized fault-tolerant access"
    },
    {
      "id": 60,
      "name": "Mitchell LLC",
      "catchPhrase": "Public-key responsive success"
    },
    {
      "id": 61,
      "name": "Kuhlman, Kovacek and Ledner",
      "catchPhrase": "Phased bifurcated encryption"
    },
    {
      "id": 62,
      "name": "Nolan, Carter and Schamberger",
      "catchPhrase": "Adaptive regional application"
    },
    {
      "id": 63,
      "name": "Kreiger Group",
      "catchPhrase": "Future-proofed disintermediate utilisation"
    },
    {
      "id": 64,
      "name": "O'Conner - Erdman",
      "catchPhrase": "Object-based analyzing intranet"
    },
    {
      "id": 65,
      "name": "Macejkovic - Graham",
      "catchPhrase": "Virtual system-worthy hardware"
    },
    {
      "id": 66,
      "name": "Wiza and Sons",
      "catchPhrase": "Phased zero defect architecture"
    },
    {
      "id": 67,
      "name": "Shanahan, Swift and Kutch",
      "catchPhrase": "Realigned radical software"
    },
    {
      "id": 68,
      "name": "Davis Inc",
      "catchPhrase": "Seamless web-enabled monitoring"
    },
    {
      "id": 69,
      "name": "Cormier, Schoen and Upton",
      "catchPhrase": "Ameliorated grid-enabled encryption"
    },
    {
      "id": 70,
      "name": "Pfannerstill and Sons",
      "catchPhrase": "Streamlined local attitude"
    },
    {
      "id": 71,
      "name": "Macejkovic - Beahan",
      "catchPhrase": "Phased full-range structure"
    },
    {
      "id": 72,
      "name": "Lubowitz Group",
      "catchPhrase": "Open-source local instruction set"
    },
    {
      "id": 73,
      "name": "Bins and Sons",
      "catchPhrase": "Open-source asynchronous matrix"
    },
    {
      "id": 74,
      "name": "Conn LLC",
      "catchPhrase": "Right-sized scalable internet solution"
    },
    {
      "id": 75,
      "name": "Glover - Durgan",
      "catchPhrase": "Quality-focused multi-tasking open system"
    },
    {
      "id": 76,
      "name": "O'Connell, Gottlieb and Hansen",
      "catchPhrase": "Distributed explicit groupware"
    },
    {
      "id": 77,
      "name": "Rutherford Group",
      "catchPhrase": "Fully-configurable disintermediate intranet"
    },
    {
      "id": 78,
      "name": "Harvey and Sons",
      "catchPhrase": "Automated radical firmware"
    },
    {
      "id": 79,
      "name": "Quigley - Harvey",
      "catchPhrase": "Switchable tertiary migration"
    },
    {
      "id": 80,
      "name": "O'Hara - Koelpin",
      "catchPhrase": "Face to face executive intranet"
    },
    {
      "id": 81,
      "name": "Hintz and Sons",
      "catchPhrase": "Phased explicit strategy"
    },
    {
      "id": 82,
      "name": "Kris Group",
      "catchPhrase": "Reduced global knowledge base"
    },
    {
      "id": 83,
      "name": "Abernathy - Hessel",
      "catchPhrase": "Streamlined actuating array"
    },
    {
      "id": 84,
      "name": "Schaefer - Lindgren",
      "catchPhrase": "Team-oriented context-sensitive encoding"
    },
    {
      "id": 85,
      "name": "Purdy, Gerhold and Keeling",
      "catchPhrase": "Open-architected mission-critical encoding"
    },
    {
      "id": 86,
      "name": "Runolfsdottir - Kunde",
      "catchPhrase": "Stand-alone well-modulated data-warehouse"
    },
    {
      "id": 87,
      "name": "Tromp - Jones",
      "catchPhrase": "Secured next generation support"
    },
    {
      "id": 88,
      "name": "Senger, Durgan and Schuppe",
      "catchPhrase": "Horizontal national moderator"
    },
    {
      "id": 89,
      "name": "Gleason - Runolfsdottir",
      "catchPhrase": "Switchable 3rd generation budgetary management"
    },
    {
      "id": 90,
      "name": "Lang - Legros",
      "catchPhrase": "Networked hybrid model"
    },
    {
      "id": 91,
      "name": "Goldner and Sons",
      "catchPhrase": "Total high-level infrastructure"
    },
    {
      "id": 92,
      "name": "West - Champlin",
      "catchPhrase": "Assimilated cohesive website"
    },
    {
      "id": 93,
      "name": "Pfannerstill - Bergstrom",
      "catchPhrase": "Persevering neutral help-desk"
    },
    {
      "id": 94,
      "name": "Wisozk - Kihn",
      "catchPhrase": "Public-key maximized workforce"
    },
    {
      "id": 95,
      "name": "Heaney, Lemke and Yundt",
      "catchPhrase": "Operative even-keeled challenge"
    },
    {
      "id": 96,
      "name": "Zboncak - Stanton",
      "catchPhrase": "Synergized grid-enabled website"
    },
    {
      "id": 97,
      "name": "Carroll - Smith",
      "catchPhrase": "Ergonomic 24/7 moderator"
    },
    {
      "id": 98,
      "name": "Mills - Kuvalis",
      "catchPhrase": "Integrated encompassing benchmark"
    },
    {
      "id": 99,
      "name": "Hansen Inc",
      "catchPhrase": "Stand-alone zero defect attitude"
    },
    {
      "id": 100,
      "name": "Bergstrom - Gerlach",
      "catchPhrase": "Public-key encompassing parallelism"
    }
  ],
  "accounts": [
    {
      "id": 1,
      "customer_id": 1,
      "accountNumber": "66984927",
      "name": "Checking Account",
      "amount": "345.41"
    },
    {
      "id": 2,
      "customer_id": 1,
      "accountNumber": "59156397",
      "name": "Personal Loan Account",
      "amount": "382.30"
    },
    {
      "id": 3,
      "customer_id": 2,
      "accountNumber": "10748822",
      "name": "Personal Loan Account",
      "amount": "356.34"
    },
    {
      "id": 4,
      "customer_id": 2,
      "accountNumber": "28525112",
      "name": "Personal Loan Account",
      "amount": "292.13"
    },
    {
      "id": 5,
      "customer_id": 3,
      "accountNumber": "58108434",
      "name": "Home Loan Account",
      "amount": "621.88"
    },
    {
      "id": 6,
      "customer_id": 4,
      "accountNumber": "72289216",
      "name": "Money Market Account",
      "amount": "343.70"
    },
    {
      "id": 7,
      "customer_id": 4,
      "accountNumber": "64118177",
      "name": "Home Loan Account",
      "amount": "638.35"
    },
    {
      "id": 8,
      "customer_id": 5,
      "accountNumber": "42734093",
      "name": "Personal Loan Account",
      "amount": "380.53"
    },
    {
      "id": 9,
      "customer_id": 5,
      "accountNumber": "61018684",
      "name": "Home Loan Account",
      "amount": "331.41"
    },
    {
      "id": 10,
      "customer_id": 5,
      "accountNumber": "54801686",
      "name": "Credit Card Account",
      "amount": "918.36"
    },
    {
      "id": 11,
      "customer_id": 6,
      "accountNumber": "56581802",
      "name": "Savings Account",
      "amount": "603.35"
    },
    {
      "id": 12,
      "customer_id": 6,
      "accountNumber": "91571960",
      "name": "Savings Account",
      "amount": "389.69"
    },
    {
      "id": 13,
      "customer_id": 7,
      "accountNumber": "85792235",
      "name": "Investment Account",
      "amount": "226.24"
    },
    {
      "id": 14,
      "customer_id": 8,
      "accountNumber": "41028720",
      "name": "Auto Loan Account",
      "amount": "990.09"
    },
    {
      "id": 15,
      "customer_id": 8,
      "accountNumber": "85880681",
      "name": "Investment Account",
      "amount": "278.38"
    },
    {
      "id": 16,
      "customer_id": 9,
      "accountNumber": "09836420",
      "name": "Savings Account",
      "amount": "611.64"
    },
    {
      "id": 17,
      "customer_id": 10,
      "accountNumber": "34656862",
      "name": "Savings Account",
      "amount": "890.77"
    },
    {
      "id": 18,
      "customer_id": 11,
      "accountNumber": "09698431",
      "name": "Money Market Account",
      "amount": "435.03"
    },
    {
      "id": 19,
      "customer_id": 12,
      "accountNumber": "66926625",
      "name": "Investment Account",
      "amount": "335.17"
    },
    {
      "id": 20,
      "customer_id": 12,
      "accountNumber": "80254583",
      "name": "Auto Loan Account",
      "amount": "564.46"
    },
    {
      "id": 21,
      "customer_id": 12,
      "accountNumber": "61932183",
      "name": "Savings Account",
      "amount": "460.84"
    },
    {
      "id": 22,
      "customer_id": 13,
      "accountNumber": "02694306",
      "name": "Home Loan Account",
      "amount": "416.24"
    },
    {
      "id": 23,
      "customer_id": 14,
      "accountNumber": "65848966",
      "name": "Auto Loan Account",
      "amount": "341.83"
    },
    {
      "id": 24,
      "customer_id": 15,
      "accountNumber": "21162620",
      "name": "Checking Account",
      "amount": "989.04"
    },
    {
      "id": 25,
      "customer_id": 15,
      "accountNumber": "04692285",
      "name": "Home Loan Account",
      "amount": "102.75"
    },
    {
      "id": 26,
      "customer_id": 16,
      "accountNumber": "79177678",
      "name": "Auto Loan Account",
      "amount": "778.62"
    },
    {
      "id": 27,
      "customer_id": 16,
      "accountNumber": "94699780",
      "name": "Checking Account",
      "amount": "552.47"
    },
    {
      "id": 28,
      "customer_id": 17,
      "accountNumber": "27564423",
      "name": "Savings Account",
      "amount": "832.57"
    },
    {
      "id": 29,
      "customer_id": 18,
      "accountNumber": "60443332",
      "name": "Personal Loan Account",
      "amount": "803.44"
    },
    {
      "id": 30,
      "customer_id": 18,
      "accountNumber": "58368035",
      "name": "Personal Loan Account",
      "amount": "29.53"
    },
    {
      "id": 31,
      "customer_id": 18,
      "accountNumber": "00166488",
      "name": "Checking Account",
      "amount": "426.51"
    },
    {
      "id": 32,
      "customer_id": 19,
      "accountNumber": "85285810",
      "name": "Money Market Account",
      "amount": "681.44"
    },
    {
      "id": 33,
      "customer_id": 20,
      "accountNumber": "77497644",
      "name": "Personal Loan Account",
      "amount": "558.70"
    },
    {
      "id": 34,
      "customer_id": 20,
      "accountNumber": "63977906",
      "name": "Personal Loan Account",
      "amount": "235.69"
    },
    {
      "id": 35,
      "customer_id": 20,
      "accountNumber": "74686004",
      "name": "Credit Card Account",
      "amount": "63.38"
    },
    {
      "id": 36,
      "customer_id": 21,
      "accountNumber": "97441752",
      "name": "Home Loan Account",
      "amount": "213.68"
    },
    {
      "id": 37,
      "customer_id": 21,
      "accountNumber": "35409013",
      "name": "Checking Account",
      "amount": "355.41"
    },
    {
      "id": 38,
      "customer_id": 22,
      "accountNumber": "03877931",
      "name": "Credit Card Account",
      "amount": "558.32"
    },
    {
      "id": 39,
      "customer_id": 23,
      "accountNumber": "62533092",
      "name": "Home Loan Account",
      "amount": "136.25"
    },
    {
      "id": 40,
      "customer_id": 24,
      "accountNumber": "76230720",
      "name": "Auto Loan Account",
      "amount": "396.62"
    },
    {
      "id": 41,
      "customer_id": 24,
      "accountNumber": "41108886",
      "name": "Home Loan Account",
      "amount": "86.21"
    },
    {
      "id": 42,
      "customer_id": 24,
      "accountNumber": "62694509",
      "name": "Money Market Account",
      "amount": "549.22"
    },
    {
      "id": 43,
      "customer_id": 25,
      "accountNumber": "95145798",
      "name": "Credit Card Account",
      "amount": "886.58"
    },
    {
      "id": 44,
      "customer_id": 25,
      "accountNumber": "67602140",
      "name": "Savings Account",
      "amount": "955.79"
    },
    {
      "id": 45,
      "customer_id": 26,
      "accountNumber": "63966958",
      "name": "Investment Account",
      "amount": "459.30"
    },
    {
      "id": 46,
      "customer_id": 27,
      "accountNumber": "04882258",
      "name": "Auto Loan Account",
      "amount": "661.43"
    },
    {
      "id": 47,
      "customer_id": 28,
      "accountNumber": "10849037",
      "name": "Investment Account",
      "amount": "405.38"
    },
    {
      "id": 48,
      "customer_id": 28,
      "accountNumber": "24650379",
      "name": "Auto Loan Account",
      "amount": "915.66"
    },
    {
      "id": 49,
      "customer_id": 28,
      "accountNumber": "98351815",
      "name": "Home Loan Account",
      "amount": "819.28"
    },
    {
      "id": 50,
      "customer_id": 29,
      "accountNumber": "56198303",
      "name": "Credit Card Account",
      "amount": "243.48"
    },
    {
      "id": 51,
      "customer_id": 29,
      "accountNumber": "14843500",
      "name": "Checking Account",
      "amount": "963.81"
    },
    {
      "id": 52,
      "customer_id": 29,
      "accountNumber": "96254184",
      "name": "Savings Account",
      "amount": "832.50"
    },
    {
      "id": 53,
      "customer_id": 30,
      "accountNumber": "93507955",
      "name": "Checking Account",
      "amount": "477.95"
    },
    {
      "id": 54,
      "customer_id": 30,
      "accountNumber": "60316219",
      "name": "Investment Account",
      "amount": "348.42"
    },
    {
      "id": 55,
      "customer_id": 31,
      "accountNumber": "05140318",
      "name": "Home Loan Account",
      "amount": "492.91"
    },
    {
      "id": 56,
      "customer_id": 31,
      "accountNumber": "93358470",
      "name": "Personal Loan Account",
      "amount": "779.86"
    },
    {
      "id": 57,
      "customer_id": 32,
      "accountNumber": "61867573",
      "name": "Home Loan Account",
      "amount": "717.29"
    },
    {
      "id": 58,
      "customer_id": 33,
      "accountNumber": "58901432",
      "name": "Checking Account",
      "amount": "496.26"
    },
    {
      "id": 59,
      "customer_id": 33,
      "accountNumber": "51783617",
      "name": "Money Market Account",
      "amount": "26.43"
    },
    {
      "id": 60,
      "customer_id": 34,
      "accountNumber": "26675751",
      "name": "Money Market Account",
      "amount": "957.04"
    },
    {
      "id": 61,
      "customer_id": 35,
      "accountNumber": "96570660",
      "name": "Money Market Account",
      "amount": "344.69"
    },
    {
      "id": 62,
      "customer_id": 36,
      "accountNumber": "38464982",
      "name": "Credit Card Account",
      "amount": "171.19"
    },
    {
      "id": 63,
      "customer_id": 36,
      "accountNumber": "58717412",
      "name": "Home Loan Account",
      "amount": "570.37"
    },
    {
      "id": 64,
      "customer_id": 37,
      "accountNumber": "56259773",
      "name": "Money Market Account",
      "amount": "851.68"
    },
    {
      "id": 65,
      "customer_id": 37,
      "accountNumber": "25489049",
      "name": "Savings Account",
      "amount": "592.43"
    },
    {
      "id": 66,
      "customer_id": 38,
      "accountNumber": "20194379",
      "name": "Money Market Account",
      "amount": "553.36"
    },
    {
      "id": 67,
      "customer_id": 39,
      "accountNumber": "78980276",
      "name": "Credit Card Account",
      "amount": "51.42"
    },
    {
      "id": 68,
      "customer_id": 39,
      "accountNumber": "36006960",
      "name": "Credit Card Account",
      "amount": "419.04"
    },
    {
      "id": 69,
      "customer_id": 40,
      "accountNumber": "77059941",
      "name": "Investment Account",
      "amount": "295.83"
    },
    {
      "id": 70,
      "customer_id": 40,
      "accountNumber": "83689684",
      "name": "Auto Loan Account",
      "amount": "915.23"
    },
    {
      "id": 71,
      "customer_id": 41,
      "accountNumber": "84771686",
      "name": "Personal Loan Account",
      "amount": "916.49"
    },
    {
      "id": 72,
      "customer_id": 41,
      "accountNumber": "30173697",
      "name": "Savings Account",
      "amount": "280.35"
    },
    {
      "id": 73,
      "customer_id": 41,
      "accountNumber": "59794271",
      "name": "Credit Card Account",
      "amount": "459.20"
    },
    {
      "id": 74,
      "customer_id": 42,
      "accountNumber": "54948591",
      "name": "Credit Card Account",
      "amount": "422.82"
    },
    {
      "id": 75,
      "customer_id": 43,
      "accountNumber": "63377686",
      "name": "Auto Loan Account",
      "amount": "917.73"
    },
    {
      "id": 76,
      "customer_id": 43,
      "accountNumber": "14766392",
      "name": "Checking Account",
      "amount": "497.82"
    },
    {
      "id": 77,
      "customer_id": 43,
      "accountNumber": "44392281",
      "name": "Investment Account",
      "amount": "320.17"
    },
    {
      "id": 78,
      "customer_id": 44,
      "accountNumber": "74664517",
      "name": "Checking Account",
      "amount": "390.79"
    },
    {
      "id": 79,
      "customer_id": 44,
      "accountNumber": "49653139",
      "name": "Savings Account",
      "amount": "945.43"
    },
    {
      "id": 80,
      "customer_id": 44,
      "accountNumber": "73858568",
      "name": "Checking Account",
      "amount": "365.65"
    },
    {
      "id": 81,
      "customer_id": 45,
      "accountNumber": "75554949",
      "name": "Investment Account",
      "amount": "54.11"
    },
    {
      "id": 82,
      "customer_id": 45,
      "accountNumber": "57325895",
      "name": "Personal Loan Account",
      "amount": "845.57"
    },
    {
      "id": 83,
      "customer_id": 46,
      "accountNumber": "16816662",
      "name": "Home Loan Account",
      "amount": "345.86"
    },
    {
      "id": 84,
      "customer_id": 46,
      "accountNumber": "74303861",
      "name": "Investment Account",
      "amount": "819.29"
    },
    {
      "id": 85,
      "customer_id": 46,
      "accountNumber": "12298205",
      "name": "Home Loan Account",
      "amount": "7.20"
    },
    {
      "id": 86,
      "customer_id": 47,
      "accountNumber": "47357587",
      "name": "Checking Account",
      "amount": "861.39"
    },
    {
      "id": 87,
      "customer_id": 47,
      "accountNumber": "76132523",
      "name": "Investment Account",
      "amount": "985.62"
    },
    {
      "id": 88,
      "customer_id": 48,
      "accountNumber": "89026674",
      "name": "Credit Card Account",
      "amount": "44.06"
    },
    {
      "id": 89,
      "customer_id": 48,
      "accountNumber": "71189185",
      "name": "Auto Loan Account",
      "amount": "373.21"
    },
    {
      "id": 90,
      "customer_id": 49,
      "accountNumber": "29199033",
      "name": "Credit Card Account",
      "amount": "735.86"
    },
    {
      "id": 91,
      "customer_id": 49,
      "accountNumber": "26566224",
      "name": "Money Market Account",
      "amount": "998.67"
    },
    {
      "id": 92,
      "customer_id": 49,
      "accountNumber": "32416551",
      "name": "Credit Card Account",
      "amount": "544.38"
    },
    {
      "id": 93,
      "customer_id": 50,
      "accountNumber": "90428951",
      "name": "Credit Card Account",
      "amount": "993.31"
    },
    {
      "id": 94,
      "customer_id": 50,
      "accountNumber": "88316677",
      "name": "Auto Loan Account",
      "amount": "998.55"
    },
    {
      "id": 95,
      "customer_id": 51,
      "accountNumber": "02806718",
      "name": "Checking Account",
      "amount": "526.41"
    },
    {
      "id": 96,
      "customer_id": 52,
      "accountNumber": "96463068",
      "name": "Money Market Account",
      "amount": "168.33"
    },
    {
      "id": 97,
      "customer_id": 53,
      "accountNumber": "95517329",
      "name": "Savings Account",
      "amount": "579.84"
    },
    {
      "id": 98,
      "customer_id": 54,
      "accountNumber": "45317397",
      "name": "Home Loan Account",
      "amount": "36.39"
    },
    {
      "id": 99,
      "customer_id": 54,
      "accountNumber": "83064446",
      "name": "Personal Loan Account",
      "amount": "624.22"
    },
    {
      "id": 100,
      "customer_id": 55,
      "accountNumber": "42171806",
      "name": "Auto Loan Account",
      "amount": "752.24"
    },
    {
      "id": 101,
      "customer_id": 56,
      "accountNumber": "76114979",
      "name": "Money Market Account",
      "amount": "885.05"
    },
    {
      "id": 102,
      "customer_id": 56,
      "accountNumber": "38970226",
      "name": "Auto Loan Account",
      "amount": "930.07"
    },
    {
      "id": 103,
      "customer_id": 57,
      "accountNumber": "47571452",
      "name": "Investment Account",
      "amount": "37.83"
    },
    {
      "id": 104,
      "customer_id": 58,
      "accountNumber": "17479932",
      "name": "Personal Loan Account",
      "amount": "494.56"
    },
    {
      "id": 105,
      "customer_id": 58,
      "accountNumber": "51064909",
      "name": "Auto Loan Account",
      "amount": "327.59"
    },
    {
      "id": 106,
      "customer_id": 58,
      "accountNumber": "01197565",
      "name": "Credit Card Account",
      "amount": "955.28"
    },
    {
      "id": 107,
      "customer_id": 59,
      "accountNumber": "00308350",
      "name": "Home Loan Account",
      "amount": "451.31"
    },
    {
      "id": 108,
      "customer_id": 60,
      "accountNumber": "03039349",
      "name": "Checking Account",
      "amount": "520.75"
    },
    {
      "id": 109,
      "customer_id": 60,
      "accountNumber": "88196698",
      "name": "Investment Account",
      "amount": "626.33"
    },
    {
      "id": 110,
      "customer_id": 61,
      "accountNumber": "77032912",
      "name": "Savings Account",
      "amount": "114.49"
    },
    {
      "id": 111,
      "customer_id": 62,
      "accountNumber": "44841428",
      "name": "Auto Loan Account",
      "amount": "17.30"
    },
    {
      "id": 112,
      "customer_id": 62,
      "accountNumber": "82998905",
      "name": "Home Loan Account",
      "amount": "752.78"
    },
    {
      "id": 113,
      "customer_id": 62,
      "accountNumber": "75306506",
      "name": "Money Market Account",
      "amount": "848.44"
    },
    {
      "id": 114,
      "customer_id": 63,
      "accountNumber": "56860586",
      "name": "Personal Loan Account",
      "amount": "337.07"
    },
    {
      "id": 115,
      "customer_id": 63,
      "accountNumber": "52138786",
      "name": "Personal Loan Account",
      "amount": "70.16"
    },
    {
      "id": 116,
      "customer_id": 63,
      "accountNumber": "22628412",
      "name": "Checking Account",
      "amount": "113.39"
    },
    {
      "id": 117,
      "customer_id": 64,
      "accountNumber": "17299583",
      "name": "Personal Loan Account",
      "amount": "415.63"
    },
    {
      "id": 118,
      "customer_id": 65,
      "accountNumber": "07945670",
      "name": "Credit Card Account",
      "amount": "719.53"
    },
    {
      "id": 119,
      "customer_id": 65,
      "accountNumber": "51055882",
      "name": "Money Market Account",
      "amount": "242.55"
    },
    {
      "id": 120,
      "customer_id": 66,
      "accountNumber": "50946350",
      "name": "Savings Account",
      "amount": "571.83"
    },
    {
      "id": 121,
      "customer_id": 67,
      "accountNumber": "00245831",
      "name": "Credit Card Account",
      "amount": "581.86"
    },
    {
      "id": 122,
      "customer_id": 67,
      "accountNumber": "05674774",
      "name": "Auto Loan Account",
      "amount": "209.87"
    },
    {
      "id": 123,
      "customer_id": 68,
      "accountNumber": "06636127",
      "name": "Savings Account",
      "amount": "967.62"
    },
    {
      "id": 124,
      "customer_id": 69,
      "accountNumber": "75941708",
      "name": "Credit Card Account",
      "amount": "514.64"
    },
    {
      "id": 125,
      "customer_id": 69,
      "accountNumber": "95963565",
      "name": "Money Market Account",
      "amount": "176.20"
    },
    {
      "id": 126,
      "customer_id": 70,
      "accountNumber": "80485592",
      "name": "Credit Card Account",
      "amount": "537.34"
    },
    {
      "id": 127,
      "customer_id": 71,
      "accountNumber": "54468917",
      "name": "Money Market Account",
      "amount": "323.07"
    },
    {
      "id": 128,
      "customer_id": 72,
      "accountNumber": "86733533",
      "name": "Credit Card Account",
      "amount": "543.42"
    },
    {
      "id": 129,
      "customer_id": 73,
      "accountNumber": "55962875",
      "name": "Money Market Account",
      "amount": "940.01"
    },
    {
      "id": 130,
      "customer_id": 73,
      "accountNumber": "41116403",
      "name": "Checking Account",
      "amount": "966.37"
    },
    {
      "id": 131,
      "customer_id": 74,
      "accountNumber": "24279657",
      "name": "Money Market Account",
      "amount": "637.86"
    },
    {
      "id": 132,
      "customer_id": 74,
      "accountNumber": "88469775",
      "name": "Investment Account",
      "amount": "67.60"
    },
    {
      "id": 133,
      "customer_id": 74,
      "accountNumber": "15212446",
      "name": "Checking Account",
      "amount": "553.73"
    },
    {
      "id": 134,
      "customer_id": 75,
      "accountNumber": "46162419",
      "name": "Checking Account",
      "amount": "254.08"
    },
    {
      "id": 135,
      "customer_id": 75,
      "accountNumber": "58167856",
      "name": "Personal Loan Account",
      "amount": "696.61"
    },
    {
      "id": 136,
      "customer_id": 75,
      "accountNumber": "03876971",
      "name": "Checking Account",
      "amount": "842.40"
    },
    {
      "id": 137,
      "customer_id": 76,
      "accountNumber": "58283219",
      "name": "Credit Card Account",
      "amount": "745.78"
    },
    {
      "id": 138,
      "customer_id": 76,
      "accountNumber": "16552343",
      "name": "Checking Account",
      "amount": "162.74"
    },
    {
      "id": 139,
      "customer_id": 77,
      "accountNumber": "20814952",
      "name": "Investment Account",
      "amount": "527.19"
    },
    {
      "id": 140,
      "customer_id": 77,
      "accountNumber": "70137938",
      "name": "Auto Loan Account",
      "amount": "375.52"
    },
    {
      "id": 141,
      "customer_id": 78,
      "accountNumber": "95459353",
      "name": "Personal Loan Account",
      "amount": "951.56"
    },
    {
      "id": 142,
      "customer_id": 79,
      "accountNumber": "59818986",
      "name": "Home Loan Account",
      "amount": "165.42"
    },
    {
      "id": 143,
      "customer_id": 80,
      "accountNumber": "18516227",
      "name": "Personal Loan Account",
      "amount": "422.63"
    },
    {
      "id": 144,
      "customer_id": 80,
      "accountNumber": "49729716",
      "name": "Personal Loan Account",
      "amount": "433.05"
    },
    {
      "id": 145,
      "customer_id": 81,
      "accountNumber": "12799574",
      "name": "Checking Account",
      "amount": "539.44"
    },
    {
      "id": 146,
      "customer_id": 81,
      "accountNumber": "18053451",
      "name": "Checking Account",
      "amount": "50.95"
    },
    {
      "id": 147,
      "customer_id": 82,
      "accountNumber": "54629282",
      "name": "Personal Loan Account",
      "amount": "958.17"
    },
    {
      "id": 148,
      "customer_id": 82,
      "accountNumber": "50353063",
      "name": "Checking Account",
      "amount": "313.19"
    },
    {
      "id": 149,
      "customer_id": 83,
      "accountNumber": "98848215",
      "name": "Credit Card Account",
      "amount": "354.43"
    },
    {
      "id": 150,
      "customer_id": 83,
      "accountNumber": "00545222",
      "name": "Investment Account",
      "amount": "545.26"
    },
    {
      "id": 151,
      "customer_id": 83,
      "accountNumber": "82408697",
      "name": "Savings Account",
      "amount": "756.49"
    },
    {
      "id": 152,
      "customer_id": 84,
      "accountNumber": "23915793",
      "name": "Auto Loan Account",
      "amount": "618.61"
    },
    {
      "id": 153,
      "customer_id": 84,
      "accountNumber": "22049877",
      "name": "Auto Loan Account",
      "amount": "112.10"
    },
    {
      "id": 154,
      "customer_id": 85,
      "accountNumber": "72702263",
      "name": "Personal Loan Account",
      "amount": "176.45"
    },
    {
      "id": 155,
      "customer_id": 86,
      "accountNumber": "78777287",
      "name": "Money Market Account",
      "amount": "823.90"
    },
    {
      "id": 156,
      "customer_id": 86,
      "accountNumber": "66606182",
      "name": "Checking Account",
      "amount": "155.91"
    },
    {
      "id": 157,
      "customer_id": 86,
      "accountNumber": "08306261",
      "name": "Money Market Account",
      "amount": "6.24"
    },
    {
      "id": 158,
      "customer_id": 87,
      "accountNumber": "84531694",
      "name": "Home Loan Account",
      "amount": "118.47"
    },
    {
      "id": 159,
      "customer_id": 87,
      "accountNumber": "28818239",
      "name": "Money Market Account",
      "amount": "499.86"
    },
    {
      "id": 160,
      "customer_id": 88,
      "accountNumber": "30961470",
      "name": "Savings Account",
      "amount": "124.58"
    },
    {
      "id": 161,
      "customer_id": 89,
      "accountNumber": "11807142",
      "name": "Home Loan Account",
      "amount": "406.71"
    },
    {
      "id": 162,
      "customer_id": 89,
      "accountNumber": "05046875",
      "name": "Home Loan Account",
      "amount": "223.84"
    },
    {
      "id": 163,
      "customer_id": 90,
      "accountNumber": "05548948",
      "name": "Auto Loan Account",
      "amount": "871.93"
    },
    {
      "id": 164,
      "customer_id": 91,
      "accountNumber": "34361618",
      "name": "Personal Loan Account",
      "amount": "921.86"
    },
    {
      "id": 165,
      "customer_id": 92,
      "accountNumber": "96354624",
      "name": "Personal Loan Account",
      "amount": "395.80"
    },
    {
      "id": 166,
      "customer_id": 92,
      "accountNumber": "54547804",
      "name": "Personal Loan Account",
      "amount": "599.91"
    },
    {
      "id": 167,
      "customer_id": 93,
      "accountNumber": "31576967",
      "name": "Credit Card Account",
      "amount": "836.21"
    },
    {
      "id": 168,
      "customer_id": 94,
      "accountNumber": "76314784",
      "name": "Personal Loan Account",
      "amount": "134.57"
    },
    {
      "id": 169,
      "customer_id": 94,
      "accountNumber": "38673506",
      "name": "Savings Account",
      "amount": "982.49"
    },
    {
      "id": 170,
      "customer_id": 95,
      "accountNumber": "20996166",
      "name": "Savings Account",
      "amount": "142.25"
    },
    {
      "id": 171,
      "customer_id": 95,
      "accountNumber": "16432709",
      "name": "Credit Card Account",
      "amount": "864.17"
    },
    {
      "id": 172,
      "customer_id": 96,
      "accountNumber": "85029180",
      "name": "Checking Account",
      "amount": "280.42"
    },
    {
      "id": 173,
      "customer_id": 96,
      "accountNumber": "37979055",
      "name": "Savings Account",
      "amount": "392.54"
    },
    {
      "id": 174,
      "customer_id": 96,
      "accountNumber": "67129945",
      "name": "Personal Loan Account",
      "amount": "894.02"
    },
    {
      "id": 175,
      "customer_id": 97,
      "accountNumber": "91966442",
      "name": "Checking Account",
      "amount": "542.95"
    },
    {
      "id": 176,
      "customer_id": 97,
      "accountNumber": "78901931",
      "name": "Personal Loan Account",
      "amount": "648.37"
    },
    {
      "id": 177,
      "customer_id": 98,
      "accountNumber": "90609792",
      "name": "Credit Card Account",
      "amount": "712.63"
    },
    {
      "id": 178,
      "customer_id": 98,
      "accountNumber": "04929714",
      "name": "Money Market Account",
      "amount": "32.78"
    },
    {
      "id": 179,
      "customer_id": 99,
      "accountNumber": "90008198",
      "name": "Savings Account",
      "amount": "222.79"
    },
    {
      "id": 180,
      "customer_id": 99,
      "accountNumber": "58311181",
      "name": "Auto Loan Account",
      "amount": "20.95"
    },
    {
      "id": 181,
      "customer_id": 100,
      "accountNumber": "99435342",
      "name": "Savings Account",
      "amount": "294.75"
    }
  ]
}
